pipo.py
pipo-0.1.0.dist-info/DESCRIPTION.rst
pipo-0.1.0.dist-info/METADATA
pipo-0.1.0.dist-info/RECORD
pipo-0.1.0.dist-info/WHEEL
pipo-0.1.0.dist-info/entry_points.txt
pipo-0.1.0.dist-info/metadata.json
pipo-0.1.0.dist-info/top_level.txt
