Metadata-Version: 1.0
Name: pipo
Version: 0.1.0
Summary: CLI helper for setuptools
Home-page: https://pypi.python.org/pypi/pipo
Author: Cyrille Rossant
Author-email: cyrille.rossant at gmail.com
License: BSD
Platform: UNKNOWN
